gibli/__init__.py
gibli/conf.py
gibli/filters.py
gibli/formatters.py
gibli/gibli.py
gibli/handlers.py
gibli-1.0.4.dist-info/METADATA
gibli-1.0.4.dist-info/WHEEL
gibli-1.0.4.dist-info/top_level.txt
gibli-1.0.4.dist-info/RECORD
