Metadata-Version: 2.1
Name: gibli
Version: 1.0.4
Summary: Very simple logging configurator
Home-page: UNKNOWN
Author: SP
Author-email: sp@foo.com
License: MIT
Platform: UNKNOWN
Classifier: License :: OSI Approved :: MIT License
Classifier: Programming Language :: Python :: 3
Classifier: Programming Language :: Python :: 3.7
Requires-Dist: voluptuous (==0.12.1)
